LICENSE
README.md
qualm.py
setup.cfg
setup.py
qualm.egg-info/PKG-INFO
qualm.egg-info/SOURCES.txt
qualm.egg-info/dependency_links.txt
qualm.egg-info/entry_points.txt
qualm.egg-info/top_level.txt