Metadata-Version: 2.1
Name: qualm
Version: 1.1.1
Summary: An esolang written in Python
Home-page: https://github.com/wilfreddv/qualm
Author: Wilfred
License: UNKNOWN
Platform: any
Classifier: Programming Language :: Python :: 3
Requires-Python: >=3.10
License-File: LICENSE
